{
  "data": [
    {
      "id": 161,
      "title": "PKG3",
      "total": "0 ر.س",
      "payment_method": "hyperpay",
      "paid_at": "2021-03-23T13:42:16.000000Z",
      "can_refund": false,
      "financial_text": "تم الإلغاء واسترجاء المبلغ",
      "order_id": 9689,
      "type": "Package",
      "status": "refunded",
      "used_session_count": 0,
      "session_count": 3
    },
    {
      "id": 160,
      "title": "PK2",
      "total": "0 ر.س",
      "payment_method": "hyperpay",
      "paid_at": "2021-03-23T13:14:18.000000Z",
      "can_refund": false,
      "financial_text": "تم الإلغاء واسترجاء المبلغ",
      "order_id": 9686,
      "type": "Package",
      "status": "refunded",
      "used_session_count": 0,
      "session_count": 3
    },
    {
      "id": 159,
      "title": "PKG1",
      "total": "0 ر.س",
      "payment_method": "hyperpay",
      "paid_at": "2021-03-23T11:42:41.000000Z",
      "can_refund": false,
      "financial_text": "تم إتمام الجلسات العلاجية",
      "order_id": 9685,
      "type": "Package",
      "status": "completed",
      "used_session_count": 3,
      "session_count": 3
    }
  ],
  "links": {
    "first": "https://backend-develop.famcare.app/api/v2/users/170/orders?page=1",
    "last": "https://backend-develop.famcare.app/api/v2/users/170/orders?page=1",
    "prev": null,
    "next": null
  },
  "meta": {
    "current_page": 1,
    "from": 1,
    "last_page": 1,
    "links": [
      {
        "url": null,
        "label": "&laquo; Previous",
        "active": false
      },
      {
        "url": "https://backend-develop.famcare.app/api/v2/users/170/orders?page=1",
        "label": "1",
        "active": true
      },
      {
        "url": null,
        "label": "Next &raquo;",
        "active": false
      }
    ],
    "path": "https://backend-develop.famcare.app/api/v2/users/170/orders",
    "per_page": 15,
    "to": 3,
    "total": 3
  }
}